toggl2pl/__init__.py
toggl2pl/__main__.py
toggl2pl/__serve__.py
toggl2pl-1.0.6.data/scripts/toggl2pl
toggl2pl-1.0.6.dist-info/LICENSE
toggl2pl-1.0.6.dist-info/METADATA
toggl2pl-1.0.6.dist-info/WHEEL
toggl2pl-1.0.6.dist-info/entry_points.txt
toggl2pl-1.0.6.dist-info/top_level.txt
toggl2pl-1.0.6.dist-info/RECORD
