Metadata-Version: 2.1
Name: toggl2pl
Version: 1.0.6
Summary: Python module and tool to simplify time entries export from Toggl into Project Laboratory
Home-page: https://github.com/pa-yourserveradmin-com/toggl2pl
Author: Andrew Poltavchenko
Author-email: pa@yourserveradmin.com
License: MIT
Platform: UNKNOWN
Classifier: Development Status :: 1 - Planning
Classifier: License :: OSI Approved :: MIT License
Classifier: Natural Language :: English
Classifier: Operating System :: OS Independent
Classifier: Programming Language :: Python :: 3 :: Only
Classifier: Programming Language :: Python :: Implementation :: CPython
Requires-Dist: certifi (==2019.9.11)
Requires-Dist: chardet (==3.0.4)
Requires-Dist: Click (==7.0)
Requires-Dist: elasticsearch (==7.0.4)
Requires-Dist: Flask (==1.1.1)
Requires-Dist: idna (==2.8)
Requires-Dist: itsdangerous (==1.1.0)
Requires-Dist: Jinja2 (==2.10.1)
Requires-Dist: MarkupSafe (==1.1.1)
Requires-Dist: Paste (==3.2.1)
Requires-Dist: PyYAML (==5.1.2)
Requires-Dist: requests (==2.22.0)
Requires-Dist: six (==1.12.0)
Requires-Dist: tabulate (==0.8.5)
Requires-Dist: tqdm (==4.36.1)
Requires-Dist: urllib3 (==1.25.6)
Requires-Dist: waitress (==1.4.3)
Requires-Dist: Werkzeug (==0.16.0)
